src/__init__.py
src/lambda_function.py
src/data/__init__.py
src/data/make_dataset.py
src/data/s3_helper.py
src/models/__init__.py
src/models/analyze_performance.py
src/models/asset_trader.py
src/models/performance_analyzer.py
src/models/train_model.py
src/models/utils.py
src/visualization/__init__.py
src/visualization/main.py
hourly_price_prediction-0.1.0.dist-info/LICENSE
hourly_price_prediction-0.1.0.dist-info/METADATA
hourly_price_prediction-0.1.0.dist-info/WHEEL
hourly_price_prediction-0.1.0.dist-info/top_level.txt
hourly_price_prediction-0.1.0.dist-info/RECORD
