Metadata-Version: 2.1
Name: hourly-price-prediction
Version: 0.1.0
Summary: Data Science Model-based trading algorithm for predicting the hourly close price of an asset
Home-page: UNKNOWN
Author: Zach Bloss
License: UNKNOWN
Platform: UNKNOWN
License-File: LICENSE
